my_algo/__init__.py
my_algo/apriory.py
my_algo/decisiontree.py
my_algo/kmeans.py
my_algo/linearreg.py
ddos_dmpa_algos-0.1.1.dist-info/METADATA
ddos_dmpa_algos-0.1.1.dist-info/WHEEL
ddos_dmpa_algos-0.1.1.dist-info/top_level.txt
ddos_dmpa_algos-0.1.1.dist-info/RECORD
