Metadata-Version: 2.1
Name: ddos-dmpa-algos
Version: 0.1.1
Author: nugget-cloud
Author-email: kunalyadav06112003@gmail.com
Requires-Dist: numpy
Requires-Dist: matplotlib
Requires-Dist: pandas
